{
  "todos": {
    "Coordinator": {
      "1": {
        "id": "1",
        "content": "Setup Telegram Bot dan API Integration",
        "details": "1. Create Telegram Bot dan get bot token 2. Setup Telegram OAuth untuk login 3. Setup database table untuk store Telegram user data 4. Add RLS policies untuk security",
        "status": "completed",
        "priority": "high"
      },
      "2": {
        "id": "2",
        "content": "Implementasi Telegram Connect UI",
        "details": "1. Add Connect Telegram button di profile/settings 2. OAuth flow untuk connect Telegram account 3. Display connected status 4. Disconnect functionality",
        "status": "completed",
        "priority": "high"
      },
      "3": {
        "id": "3",
        "content": "Setup Telegram Notification System",
        "details": "1. Edge Function untuk send notifications ke Telegram 2. Real-time trade alerts via Telegram 3. Custom alert preferences (per trader) 4. Alert frequency controls",
        "status": "completed",
        "priority": "high"
      },
      "4": {
        "id": "4",
        "content": "Integrasi dengan existing alerts system",
        "details": "1. Update alerts page dengan Telegram preferences 2. Send both in-app dan Telegram notifications 3. Alert templates untuk Telegram messages 4. User notification preferences",
        "status": "completed",
        "priority": "medium"
      },
      "5": {
        "id": "5",
        "content": "Testing dan deployment",
        "details": "1. Test Telegram bot integration (SEDANG MENUNGGU BOT TOKEN) 2. Test notifications delivery 3. Security testing ✅ DONE 4. Deploy updates ✅ DONE",
        "status": "in_progress",
        "priority": "medium"
      }
    }
  }
}